{
"type": "FeatureCollection",
"name": "sampel_minimarket",
"crs": { "type": "name", "properties": { "name": "urn:ogc:def:crs:OGC:1.3:CRS84" } },
"features": [
{ "type": "Feature", "properties": { "id": "node/11290931869", "addr:city": null, "addr:district": null, "name": "Alfamart", "shop": "convenience", "longitude": 106.74454, "latitude": -6.27349, "akses_tol": "Mudah Diakses" }, "geometry": { "type": "Point", "coordinates": [ 106.7445435, -6.2734929 ] } },
{ "type": "Feature", "properties": { "id": "node/4437324209", "addr:city": null, "addr:district": null, "name": "Indomaret", "shop": "convenience", "longitude": 106.74465, "latitude": -6.27387, "akses_tol": "Mudah Diakses" }, "geometry": { "type": "Point", "coordinates": [ 106.7446482, -6.2738668 ] } }
]
}
